filswan_miner/__init__.py
filswan_miner/aria2_service.py
filswan_miner/aria2c.py
filswan_miner/swan_miner.py
filswan_miner/swan_miner_deal_downloader.py
filswan_miner/swan_miner_deal_importer.py
filswan_miner/swan_miner_deal_scanner.py
filswan_miner/common/Miner.py
filswan_miner/common/OfflineDeal.py
filswan_miner/common/__init__.py
filswan_miner/common/config.py
filswan_miner/common/logging.py
filswan_miner/common/swan_client.py
filswan_miner-0.3.data/data/filswan/miner/config/config.toml
filswan_miner-0.3.dist-info/LICENSE
filswan_miner-0.3.dist-info/METADATA
filswan_miner-0.3.dist-info/WHEEL
filswan_miner-0.3.dist-info/top_level.txt
filswan_miner-0.3.dist-info/RECORD
