Metadata-Version: 2.1
Name: filswan-miner
Version: 0.3
Summary: Swan Miner tool
Home-page: https://github.com/nebulaai/swan-miner
Author: nbfs
Author-email: account@nbai.io
License: UNKNOWN
Platform: UNKNOWN
Classifier: Programming Language :: Python :: 3
Classifier: License :: OSI Approved :: MIT License
Classifier: Operating System :: OS Independent
License-File: LICENSE
Requires-Dist: toml
Requires-Dist: requests
Requires-Dist: APScheduler (~=3.6.3)
